{
    "1": {
        "id": 1,
        "name": "Sozialkompass",
        "timeframe": "September 2022 - heute",
        "image": [{
            "path":"Sozialkompass.png",
            "alt": "Die Startseite des Sozialkompass."
            },
            {
                "path":"Website.png",
                "alt": "Die Startseite des Sozialkompass."
            }],
        "description": ["Der Sozialkompass ist eine Webseite, welche Menschen in sozialen Notlagen hilft, sich über ihnen zustehende Sozialleistungen zu informieren. ",
                        "Das Projekt startete im Jahr 2022 im Rahmen eines Projektseminars an der Universität Münster und wird seit April 2023 ehrenamtlich weitergeführt.",
                        "Wir haben beim MÜNSTERHACK 2022 den zweiten Platz und Mentorenpreis gewonnen. Des Weiteren wurden wir in das Solution-Enabler-Programm des Hackathons aufgenommen und haben beim MÜNSTERHACK 2023 den Nachgehackt-Preis für das am besten weitergeführte Projekt gewonnen."
                        ],
        "myWork": ["PLACEHOLDER."],
        "technologies": ["React.js", "Next.js", "Tailwind CSS", "TypeScript", "MongoDB", "Git", "Jira", "Figma"],
        "links": [
            {
                "name": "Webseite",
                "url": "https://www.sozialkompass.info"
            },
            {
                "name": "Interview",
                "url": "https://www.digitalhub.ms/stories/portraits/2023-08-08/muensterhack-solution-enabler-sozialkompass"
            }
        ]   
    },
    "2":{
        "id": 2,
        "name": "Infosdisplay für das OVG",
        "timeframe": "Juli 2023 - November 2023",
        "image": [{
            "path":"OVGDisplay.JPEG",
            "alt": "Die Anzeige in der Haupthalle des Oberverwaltungsgerichts."
            }],
        "description": ["Für meinen Arbeitgeber, das Oberverwaltungsgericht für das Land Nordrhein-Westfalen in Münster, habe ich eine Informationsanzeige, welche im Eingangsbereich und in der Kantine des Gerichts aufgestellt ist, entwickelt.",
                        "Die Anzeige zeigt aktuelle Nachrichten, die Wettervorhersage und die aktuellen Termine des Gerichts an."
                        ],
        "myWork": ["Ich habe das Projekt vollständig alleine designed und entwickelt. Die Anzeige wird auf einem Raspberry Pi gehostet und angezeigt."],
        "technologies": ["React.js", "Vite.js", "Material UI", "Git", "Javascript"],
        "links": [
            {
                "name": "GitHub",
                "url": "https://github.com/JonasRettig/ovg-display"
            }
        ]   
    },
    "3":{
        "id": 3,
        "name": "Design Thinking Vertiefungsmodul",
        "timeframe": "Juli 2023",
        "image": [{
            "path":"Website.png",
            "alt": "Die Startseite meiner Webseite."
            }],
        "description": ["Ein Vertiefungsmodul an der Universität Münster, welches sich mit dem Thema Design Thinking beschäftigt. ",
                        "Das Seminar fand in Kooperation mit der University of West Georgia und der Georgia College & State University als Erasmus+ Projekt statt. ",
                        "Im Rahmen des Moduls haben wir vor Ort (Atlanta, USA) mit den Praxispartnern Southwire und Celonis eine reales Problem bearbeitet."
                    ],
        "myWork": ["Ich habe die Kartenansicht für diese App entwickelt. Die Karte zeigt die Abgabestellen an und wird je nach Zoom Level dynamisch mit mit Daten bereichert."],
        "technologies": ["Design Thinking", "Englisch", "Kollaboration in internationalen Teams", "Stakeholderkommuikation"],
        "links": [
            {
                "name": "Projektblog",
                "url": "https://www.dt-seminar.net/"
            },
            {
                "name": "Blogpost der GCSU",
                "url": "https://frontpage.gcsu.edu/node/14943"
            }
        ]
    },
    "4":{
        "id": 4,
        "name": "Persönliche Webseite",
        "timeframe": "Januar 2024",
        "image": [{
            "path":"Website.png",
            "alt": "Die Startseite meiner Webseite."
            }],
        "imageAlt": "",
        "description": ["Ich habe diese Webseite mit dem Ziel erstellt, meine Projekte und mich selbst vorzustellen."],
        "myWork": ["Ich habe das Projekt vollständig alleine designed und entwickelt."],
        "technologies": ["React.js", "Tailwind CSS", "Git", "TypeScript", "Next.js"],
        "links": [
            {
                "name": "GitHub",
                "url": "https://github.com/JonasRettig/jrettig.dev"
            },
            {
                "name": "Webseite",
                "url": "/"
            }
        ]
    },
    "5":{
        "id": 5,
        "name": "Hin und Weg",
        "timeframe": "September 2023",
        "image": [{
            "path":"Website.png",
            "alt": "Die Startseite meiner Webseite."
            }],
        "description": ["Im Rahmen des MÜNSTERHACK 2023 habe ich mit meinem Team eine App entwickelt, welche Abgabestellen für nicht mehr benötigte Gegenstände anzeigt. ",
                        "Ziel ist es zu verhindern, dass diese Gegenstände weggeworfen werden."
                    ],
        "myWork": ["Ich habe die Kartenansicht für diese App entwickelt. Die Karte zeigt die Abgabestellen an und wird je nach Zoom Level dynamisch mit mit Daten bereichert."],
        "technologies": ["React Native", "Test"]
    }
}